{"assets":{"714201C3887B4671BD37A950058914FB":{"type":"texture","index":1,"url":{"native":"assets\/CAFAE5FC-E1EC-4572-AFF9-7852510E1A3A.pdf"},"width":1920,"height":1080},"F1E5671D910705E4E0B5F6726F282E57":{"type":"texture","index":0,"url":{"native":"assets\/CAFAE5FC-E1EC-4572-AFF9-7852510E1A3A.pdf"},"width":1920,"height":1080}},"events":[{"effects":[{"beginTime":0,"baseLayer":{"animations":[],"initialState":{"affineTransform":[1,0,0,1,0,0],"masksToBounds":false,"rotation":0,"scale":1,"position":{"pointX":960,"pointY":540},"width":1920,"sublayerTransform":[1,0,0,0,0,1,0,0,0,0,1,0,0,0,0,1],"contentsRect":{"y":0,"x":0,"width":1,"height":1},"opacity":1,"edgeAntialiasingMask":251658240,"height":1080,"hidden":false,"anchorPoint":{"pointX":0.5,"pointY":0.5}},"objectID":"0","layers":[{"animations":[],"initialState":{"affineTransform":[1,0,0,1,0,0],"masksToBounds":false,"rotation":0,"scale":1,"position":{"pointX":960,"pointY":540},"width":1920,"sublayerTransform":[1,0,0,0,0,1,0,0,0,0,1,-0.00035007912466775983,0,0,0,1],"contentsRect":{"y":0,"x":0,"width":1,"height":1},"opacity":1,"edgeAntialiasingMask":251658240,"height":1080,"hidden":false,"anchorPoint":{"pointX":0.5,"pointY":0.5}},"layers":[{"animations":[],"layers":[],"texturedRectangle":{"isBackgroundTexture":false,"singleTextureOpacity":1,"textureType":0,"textBaseline":0,"textXHeight":0,"isVerticalText":false},"initialState":{"affineTransform":[1,0,0,1,0,0],"masksToBounds":false,"rotation":0,"scale":1,"position":{"pointX":960,"pointY":540},"width":1920,"sublayerTransform":[1,0,0,0,0,1,0,0,0,0,1,0,0,0,0,1],"contentsRect":{"y":0,"x":0,"width":1,"height":1},"opacity":1,"edgeAntialiasingMask":0,"height":1080,"hidden":false,"anchorPoint":{"pointX":0.5,"pointY":0.5}},"texture":"714201C3887B4671BD37A950058914FB"},{"animations":[{"additive":false,"timeOffset":0,"beginTime":0,"from":{"scalar":false},"repeatCount":0,"fillMode":"both","duration":0.01,"autoreverses":false,"property":"hidden","to":{"scalar":true},"removedOnCompletion":false}],"layers":[],"texturedRectangle":{"isBackgroundTexture":false,"singleTextureOpacity":1,"textureType":0,"textBaseline":0,"textXHeight":0,"isVerticalText":false},"initialState":{"affineTransform":[1,0,0,1,0,0],"masksToBounds":false,"rotation":0,"scale":1,"position":{"pointX":960,"pointY":540},"width":1920,"sublayerTransform":[1,0,0,0,0,1,0,0,0,0,1,0,0,0,0,1],"contentsRect":{"y":0,"x":0,"width":1,"height":1},"opacity":1,"edgeAntialiasingMask":0,"height":1080,"hidden":false,"anchorPoint":{"pointX":0.5,"pointY":0.5}},"texture":"F1E5671D910705E4E0B5F6726F282E57"}]}]},"effects":[],"duration":0.01,"type":"transition","attributes":{"direction":0},"name":"none","objectID":"0"}],"automaticPlay":false,"hyperlinks":[],"accessibility":[{"text":"pasted-image.tiff","targetRectangle":{"y":330.26300048828125,"x":25.82916259765625,"width":450,"height":300}},{"text":"Logo_black-1-1024x154.png","targetRectangle":{"y":37.883773803710938,"x":1283.035888671875,"width":580.96405029296875,"height":87.371543884277344}},{"text":"pasted-image.tiff","targetRectangle":{"y":628,"x":69.2523193359375,"width":400.7476806640625,"height":400.7476806640625}},{"text":"pasted-image.tiff","targetRectangle":{"y":622,"x":529.36395263671875,"width":359.078125,"height":359.078125}},{"text":"pasted-image.tiff","targetRectangle":{"y":400.08642578125,"x":453,"width":450,"height":160.35313415527344}},{"text":"pasted-image.tiff","targetRectangle":{"y":438.57383918762207,"x":1392.129753112793,"width":245.25016784667969,"height":246.27203369140625}},{"text":"pasted-image.tiff","targetRectangle":{"y":113.80095672607422,"x":103.1583251953125,"width":295.3416748046875,"height":196.72502136230469}},{"text":"pasted-image.tiff","targetRectangle":{"y":142.89618301391602,"x":1322.5096435546875,"width":384.49038696289062,"height":256.32693481445312}},{"text":"pasted-image.tiff","targetRectangle":{"y":135.15130615234375,"x":493.17083740234375,"width":369.6583251953125,"height":154.02430725097656}},{"text":"pasted-image.tiff","targetRectangle":{"y":411.8365478515625,"x":947.80609130859375,"width":256.32693481445312,"height":256.32693481445312}},{"text":"pasted-image.tiff","targetRectangle":{"y":70,"x":957.5,"width":236.93910217285156,"height":284.32693481445312}},{"text":"pasted-image.tiff","targetRectangle":{"y":652.07244873046875,"x":941.9769287109375,"width":520.6937255859375,"height":390.52029418945312}},{"text":"pasted-image.tiff","targetRectangle":{"y":748.19659423828125,"x":1516.2054443359375,"width":246.27203369140625,"height":246.27203369140625}}],"baseLayer":{"animations":[],"initialState":{"affineTransform":[1,0,0,1,0,0],"masksToBounds":false,"rotation":0,"scale":1,"position":{"pointX":960,"pointY":540},"width":1920,"sublayerTransform":[1,0,0,0,0,1,0,0,0,0,1,0,0,0,0,1],"contentsRect":{"y":0,"x":0,"width":1,"height":1},"opacity":1,"edgeAntialiasingMask":251658240,"height":1080,"hidden":false,"anchorPoint":{"pointX":0.5,"pointY":0.5}},"objectID":"0","layers":[{"animations":[],"initialState":{"affineTransform":[1,0,0,1,0,0],"masksToBounds":false,"rotation":0,"scale":1,"position":{"pointX":960,"pointY":540},"width":1920,"sublayerTransform":[1,0,0,0,0,1,0,0,0,0,1,-0.00035007912466775983,0,0,0,1],"contentsRect":{"y":0,"x":0,"width":1,"height":1},"opacity":1,"edgeAntialiasingMask":251658240,"height":1080,"hidden":false,"anchorPoint":{"pointX":0.5,"pointY":0.5}},"layers":[{"animations":[],"layers":[],"texturedRectangle":{"isBackgroundTexture":false,"singleTextureOpacity":1,"textureType":0,"textBaseline":0,"textXHeight":0,"isVerticalText":false},"initialState":{"affineTransform":[1,0,0,1,0,0],"masksToBounds":false,"rotation":0,"scale":1,"position":{"pointX":960,"pointY":540},"width":1920,"sublayerTransform":[1,0,0,0,0,1,0,0,0,0,1,0,0,0,0,1],"contentsRect":{"y":0,"x":0,"width":1,"height":1},"opacity":1,"edgeAntialiasingMask":0,"height":1080,"hidden":false,"anchorPoint":{"pointX":0.5,"pointY":0.5}},"texture":"F1E5671D910705E4E0B5F6726F282E57"}]}]}}]}